LICENSE
pseudonymize_pdf.py
pseudonymize_pdf-0.3.1.dist-info/LICENSE
pseudonymize_pdf-0.3.1.dist-info/WHEEL
pseudonymize_pdf-0.3.1.dist-info/METADATA
pseudonymize_pdf-0.3.1.dist-info/RECORD
