Metadata-Version: 2.1
Name: pseudonymize-pdf
Version: 0.3.1
Summary: A convenience library to read and alter PDFs to remove personally identifying data
Home-page: https://github.com/vitalbeats/pseudonymize-pdf
License: GPL-3.0-or-later
Keywords: pdf
Author: Stephen Badger
Author-email: stephen.badger@vitalbeats.com
Requires-Python: >=3.7,<4.0
Classifier: Development Status :: 3 - Alpha
Classifier: License :: OSI Approved :: GNU General Public License v3 or later (GPLv3+)
Classifier: Programming Language :: Python :: 3
Classifier: Programming Language :: Python :: 3.7
Classifier: Programming Language :: Python :: 3.8
Classifier: Topic :: Text Processing
Requires-Dist: pdf-redactor (>=0.0.1,<0.0.2)
Project-URL: Repository, https://github.com/vitalbeats/pseudonymize-pdf
